text_to_identifier.py
text_to_identifier-0.1.0a1.dist-info/licenses/LICENSE
text_to_identifier-0.1.0a1.dist-info/METADATA
text_to_identifier-0.1.0a1.dist-info/WHEEL
text_to_identifier-0.1.0a1.dist-info/top_level.txt
text_to_identifier-0.1.0a1.dist-info/RECORD
