Metadata-Version: 2.4
Name: text-to-identifier
Version: 0.1.0a1
Summary: A tool that converts arbitrary text (like user input or file names) into valid Python identifiers while preserving as much of the original meaning as possible.
Author-email: Jifeng Wu <jifengwu2k@gmail.com>
License-Expression: MIT
Project-URL: Homepage, https://github.com/jifengwu2k/text-to-identifier
Project-URL: Bug Tracker, https://github.com/jifengwu2k/text-to-identifier/issues
Classifier: Programming Language :: Python :: 2
Classifier: Programming Language :: Python :: 3
Classifier: Operating System :: OS Independent
Requires-Python: >=2
License-File: LICENSE
Requires-Dist: enum34; python_version < "3.4"
Requires-Dist: typing; python_version < "3.5"
Dynamic: license-file
